draggan/__init__.py
draggan/draggan.py
draggan/utils.py
draggan/web.py
draggan/deprecated/__init__.py
draggan/deprecated/api.py
draggan/deprecated/utils.py
draggan/deprecated/web.py
draggan/deprecated/stylegan2/__init__.py
draggan/deprecated/stylegan2/inversion.py
draggan/deprecated/stylegan2/model.py
draggan/deprecated/stylegan2/lpips/__init__.py
draggan/deprecated/stylegan2/lpips/base_model.py
draggan/deprecated/stylegan2/lpips/dist_model.py
draggan/deprecated/stylegan2/lpips/networks_basic.py
draggan/deprecated/stylegan2/lpips/pretrained_networks.py
draggan/deprecated/stylegan2/lpips/util.py
draggan/deprecated/stylegan2/op/__init__.py
draggan/deprecated/stylegan2/op/conv2d_gradfix.py
draggan/deprecated/stylegan2/op/fused_act.py
draggan/deprecated/stylegan2/op/fused_bias_act.cpp
draggan/deprecated/stylegan2/op/fused_bias_act_kernel.cu
draggan/deprecated/stylegan2/op/upfirdn2d.cpp
draggan/deprecated/stylegan2/op/upfirdn2d.py
draggan/deprecated/stylegan2/op/upfirdn2d_kernel.cu
draggan/projection/__init__.py
draggan/stylegan2/__init__.py
draggan/stylegan2/legacy.py
draggan/stylegan2/dnnlib/__init__.py
draggan/stylegan2/dnnlib/util.py
draggan/stylegan2/torch_utils/__init__.py
draggan/stylegan2/torch_utils/custom_ops.py
draggan/stylegan2/torch_utils/misc.py
draggan/stylegan2/torch_utils/persistence.py
draggan/stylegan2/torch_utils/training_stats.py
draggan/stylegan2/torch_utils/ops/__init__.py
draggan/stylegan2/torch_utils/ops/bias_act.cpp
draggan/stylegan2/torch_utils/ops/bias_act.cu
draggan/stylegan2/torch_utils/ops/bias_act.h
draggan/stylegan2/torch_utils/ops/bias_act.py
draggan/stylegan2/torch_utils/ops/conv2d_gradfix.py
draggan/stylegan2/torch_utils/ops/conv2d_resample.py
draggan/stylegan2/torch_utils/ops/fma.py
draggan/stylegan2/torch_utils/ops/grid_sample_gradfix.py
draggan/stylegan2/torch_utils/ops/upfirdn2d.cpp
draggan/stylegan2/torch_utils/ops/upfirdn2d.cu
draggan/stylegan2/torch_utils/ops/upfirdn2d.h
draggan/stylegan2/torch_utils/ops/upfirdn2d.py
draggan-1.1.6.dist-info/METADATA
draggan-1.1.6.dist-info/WHEEL
draggan-1.1.6.dist-info/top_level.txt
draggan-1.1.6.dist-info/RECORD
